kukur/__init__.py
kukur/app.py
kukur/base.py
kukur/cli.py
kukur/client.py
kukur/config.py
kukur/exceptions.py
kukur/flight.py
kukur/loader.py
kukur/logging.py
kukur/py.typed
kukur/api_key/__init__.py
kukur/api_key/app.py
kukur/inspect/__init__.py
kukur/inspect/adls.py
kukur/inspect/arrow.py
kukur/inspect/blob.py
kukur/inspect/filesystem.py
kukur/inspect/s3.py
kukur/metadata/__init__.py
kukur/metadata/fields.py
kukur/repository/__init__.py
kukur/repository/api_key.py
kukur/repository/base.py
kukur/source/__init__.py
kukur/source/arrow.py
kukur/source/metadata.py
kukur/source/quality.py
kukur/source/sql.py
kukur/source/test.py
kukur/source/adodb/__init__.py
kukur/source/adodb/adodb.py
kukur/source/arrows/__init__.py
kukur/source/arrows/arrows.py
kukur/source/azure_data_explorer/__init__.py
kukur/source/azure_data_explorer/azure_data_explorer.py
kukur/source/cratedb/__init__.py
kukur/source/cratedb/cratedb.py
kukur/source/csv/__init__.py
kukur/source/csv/csv.py
kukur/source/datafusion/__init__.py
kukur/source/datafusion/datafusion.py
kukur/source/delta/__init__.py
kukur/source/delta/delta_lake.py
kukur/source/feather/__init__.py
kukur/source/feather/feather.py
kukur/source/influxdb/__init__.py
kukur/source/influxdb/influxdb.py
kukur/source/integration_test/__init__.py
kukur/source/integration_test/integration_test_source.py
kukur/source/json/__init__.py
kukur/source/json/json.py
kukur/source/kukur/__init__.py
kukur/source/kukur/kukur.py
kukur/source/odbc/__init__.py
kukur/source/odbc/odbc.py
kukur/source/parquet/__init__.py
kukur/source/parquet/parquet.py
kukur/source/piwebapi_da/__init__.py
kukur/source/piwebapi_da/piwebapi_da.py
kukur/source/plugin/__init__.py
kukur/source/plugin/plugin.py
kukur/source/postgresql/__init__.py
kukur/source/postgresql/postgresql.py
kukur/source/redshift/__init__.py
kukur/source/redshift/redshift.py
kukur/source/simulator/__init__.py
kukur/source/simulator/simulator.py
kukur/source/sqlite/__init__.py
kukur/source/sqlite/sqlite.py
kukur-0.1.20.dist-info/LICENSE
kukur-0.1.20.dist-info/METADATA
kukur-0.1.20.dist-info/WHEEL
kukur-0.1.20.dist-info/entry_points.txt
kukur-0.1.20.dist-info/top_level.txt
kukur-0.1.20.dist-info/RECORD
