Metadata-Version: 2.1
Name: kukur
Version: 0.1.20
Summary: Kukur makes time series data and metadata available to the Apache Arrow ecosystem.
Home-page: https://kukur.timeseer.ai/
Author: Timeseer.AI
Author-email: pypi@timeseer.ai
License: Apache-2.0
Platform: UNKNOWN
Classifier: Programming Language :: Python :: 3
Classifier: Operating System :: OS Independent
Classifier: License :: OSI Approved :: Apache Software License
Requires-Python: >=3.9
License-File: LICENSE
Requires-Dist: pyarrow
Requires-Dist: python-dateutil
Requires-Dist: pytz
Requires-Dist: toml
Provides-Extra: adodb
Requires-Dist: pywin32 ; extra == 'adodb'
Provides-Extra: cratedb
Requires-Dist: crate ; extra == 'cratedb'
Provides-Extra: datafusion
Requires-Dist: datafusion ; extra == 'datafusion'
Provides-Extra: delta
Requires-Dist: deltalake ; extra == 'delta'
Provides-Extra: influxdb
Requires-Dist: influxdb ; extra == 'influxdb'
Provides-Extra: inspect
Requires-Dist: azure-storage-file-datalake ; extra == 'inspect'
Requires-Dist: adlfs ; extra == 'inspect'
Provides-Extra: kusto
Requires-Dist: azure-identity ; extra == 'kusto'
Requires-Dist: azure-kusto-data ; extra == 'kusto'
Provides-Extra: odbc
Requires-Dist: pyodbc ; extra == 'odbc'
Provides-Extra: piwebapi
Requires-Dist: requests ; extra == 'piwebapi'
Requires-Dist: requests-kerberos ; extra == 'piwebapi'
Provides-Extra: postgresql
Requires-Dist: psycopg[binary] ; extra == 'postgresql'
Provides-Extra: redshift
Requires-Dist: redshift-connector ; extra == 'redshift'
